pwnedpasswords/__init__.py
pwnedpasswords/exceptions.py
pwnedpasswords/metadata.py
pwnedpasswords/pwnedpasswords.py
pwnedpasswords-3.0.0.data/scripts/pwnedpasswords
pwnedpasswords-3.0.0.dist-info/licenses/LICENSE
pwnedpasswords-3.0.0.dist-info/licenses/NOTICE
pwnedpasswords-3.0.0.dist-info/METADATA
pwnedpasswords-3.0.0.dist-info/WHEEL
pwnedpasswords-3.0.0.dist-info/top_level.txt
pwnedpasswords-3.0.0.dist-info/RECORD
